LICENSE
README.md
setup.py
paddle_nnAudio.egg-info/PKG-INFO
paddle_nnAudio.egg-info/SOURCES.txt
paddle_nnAudio.egg-info/dependency_links.txt
paddle_nnAudio.egg-info/requires.txt
paddle_nnAudio.egg-info/top_level.txt
ppAudio/Spectrogram.py
ppAudio/__init__.py
ppAudio/librosa_functions.py
ppAudio/utils.py
ppAudio/features/__init__.py
ppAudio/features/cfp.py
ppAudio/features/cqt.py
ppAudio/features/gammatone.py
ppAudio/features/griffin_lim.py
ppAudio/features/mel.py
ppAudio/features/stft.py
ppAudio/features/vqt.py
tests/test_cfp.py
tests/test_cqt.py
tests/test_stft.py
tests/test_vqt.py
tests/tests_mel.py