Metadata-Version: 2.4
Name: paddle_nnAudio
Version: 0.0.3
Summary: A fast GPU audio processing toolbox with 1D convolutional neural network
Home-page: https://github.com/PlumBlossomMaid/ppAudio
Author: PlumBlossom
Author-email: 1589524335@qq.com
Classifier: Programming Language :: Python :: 3
Classifier: License :: OSI Approved :: MIT License
Classifier: Operating System :: OS Independent
Requires-Python: >=3.6
License-File: LICENSE
Requires-Dist: scipy>=1.2.0
Requires-Dist: numpy>=1.14.5
Provides-Extra: tests
Requires-Dist: pytest; extra == "tests"
Requires-Dist: librosa; extra == "tests"
Dynamic: author
Dynamic: author-email
Dynamic: classifier
Dynamic: description
Dynamic: description-content-type
Dynamic: home-page
Dynamic: license-file
Dynamic: provides-extra
Dynamic: requires-dist
Dynamic: requires-python
Dynamic: summary
